integration_test/__init__.py
integration_test/helper.py
integration_test/test_parameters.py
integration_test/test_statics.py
integration_test/test_websocket.py
shallot/__init__.py
shallot/response.py
shallot/ring.py
shallot/websocket.py
shallot/middlewares/__init__.py
shallot/middlewares/content_type.py
shallot/middlewares/cookies.py
shallot/middlewares/cors.py
shallot/middlewares/json.py
shallot/middlewares/parameters.py
shallot/middlewares/routing.py
shallot/middlewares/staticfiles.py
test/__init__.py
test/conftest.py
test/test_content_type.py
test/test_cookies.py
test/test_dos.py
test/test_json.py
test/test_parameters.py
test/test_response.py
test/test_ring.py
test/test_routing.py
test/test_staticfiles.py
test/test_websocket.py
shallot-2.0.0.dist-info/METADATA
shallot-2.0.0.dist-info/WHEEL
shallot-2.0.0.dist-info/top_level.txt
shallot-2.0.0.dist-info/RECORD
