Metadata-Version: 2.4
Name: shallot
Version: 2.0.0
Summary: Fast, small ASGI-compliant webframework
Home-page: https://github.com/peterpeter5/shallot
Author: Peter Peter
Author-email: dev.peterpeter5@gmail.com
Classifier: Programming Language :: Python :: 3
Requires-Python: >=3.6
Requires-Dist: aiofiles
Provides-Extra: full
Requires-Dist: uvicorn; extra == "full"
Provides-Extra: test
Requires-Dist: pytest; extra == "test"
Requires-Dist: hypothesis; extra == "test"
Requires-Dist: requests; extra == "test"
Requires-Dist: pytest-asyncio; extra == "test"
Requires-Dist: pytest-cov; extra == "test"
Requires-Dist: websockets; extra == "test"
Requires-Dist: uvicorn; extra == "test"
Provides-Extra: docs
Requires-Dist: sphinx; extra == "docs"
Requires-Dist: recommonmark; extra == "docs"
Dynamic: author
Dynamic: author-email
Dynamic: classifier
Dynamic: description
Dynamic: description-content-type
Dynamic: home-page
Dynamic: provides-extra
Dynamic: requires-dist
Dynamic: requires-python
Dynamic: summary
